enlopy/__init__.py
enlopy/analysis.py
enlopy/generate.py
enlopy/plot.py
enlopy/stats.py
enlopy/utils.py
enlopy-0.1.dist-info/LICENSE
enlopy-0.1.dist-info/METADATA
enlopy-0.1.dist-info/WHEEL
enlopy-0.1.dist-info/top_level.txt
enlopy-0.1.dist-info/RECORD
