Metadata-Version: 2.1
Name: enlopy
Version: 0.1
Summary: Python library with methods to generate, process, analyze, and plot energy related timeseries.
Home-page: https://github.com/kavvkon/enlopy
Author: Konstantinos Kavvadias
Author-email: kavvkon@gmail.com
License: BSD-3-Clause
Keywords: energy,timeseries,statistics,profile,demand
Classifier: Development Status :: 3 - Alpha
Classifier: Intended Audience :: Developers
Classifier: Intended Audience :: Science/Research
Classifier: Topic :: Utilities
Classifier: Topic :: Scientific/Engineering :: Mathematics
Classifier: Topic :: Scientific/Engineering :: Visualization
Classifier: Topic :: Software Development :: Libraries :: Python Modules
Classifier: Natural Language :: English
Classifier: License :: OSI Approved :: BSD License
Classifier: Programming Language :: Python :: 3.9
Classifier: Programming Language :: Python :: 3.10
Classifier: Programming Language :: Python :: 3.11
Classifier: Programming Language :: Python :: 3.12
Requires-Python: >=3.9
License-File: LICENSE
Requires-Dist: numpy >=1.10
Requires-Dist: scipy >=1.10
Requires-Dist: matplotlib >=2.2
Requires-Dist: pandas >=2.0
